alpha_automl/__init__.py
alpha_automl/_optional_dependency.py
alpha_automl/automl_api.py
alpha_automl/automl_manager.py
alpha_automl/base_primitive.py
alpha_automl/data_profiler.py
alpha_automl/grammar_loader.py
alpha_automl/pipeline.py
alpha_automl/pipeline_serializer.py
alpha_automl/primitive_loader.py
alpha_automl/scorer.py
alpha_automl/utils.py
alpha_automl/visualization.py
alpha_automl/builtin_primitives/__init__.py
alpha_automl/builtin_primitives/datetime_encoder.py
alpha_automl/builtin_primitives/image_encoder.py
alpha_automl/builtin_primitives/semisupervised_classifier.py
alpha_automl/builtin_primitives/time_series_forecasting.py
alpha_automl/hyperparameter_tuning/__init__.py
alpha_automl/hyperparameter_tuning/bayesian.py
alpha_automl/metalearning/__init__.py
alpha_automl/metalearning/dataset_profiler.py
alpha_automl/metalearning/dataset_similarity.py
alpha_automl/metalearning/grammar_builder.py
alpha_automl/metalearning/nnet_trainer.py
alpha_automl/metalearning/resource_builder.py
alpha_automl/pipeline_search/Arena.py
alpha_automl/pipeline_search/Coach.py
alpha_automl/pipeline_search/Game.py
alpha_automl/pipeline_search/MCTS.py
alpha_automl/pipeline_search/NeuralNet.py
alpha_automl/pipeline_search/__init__.py
alpha_automl/pipeline_search/utils.py
alpha_automl/pipeline_search/pipeline/NNet.py
alpha_automl/pipeline_search/pipeline/PipelineGame.py
alpha_automl/pipeline_search/pipeline/PipelineLogic.py
alpha_automl/pipeline_search/pipeline/PipelineNNet.py
alpha_automl/pipeline_search/pipeline/PipelinePlayers.py
alpha_automl/pipeline_search/pipeline/__init__.py
alpha_automl/pipeline_synthesis/__init__.py
alpha_automl/pipeline_synthesis/pipeline_builder.py
alpha_automl/pipeline_synthesis/setup_search.py
alpha_automl/resource/base_grammar.bnf
alpha_automl/resource/primitives_hierarchy.json
alpha_automl/wrapper_primitives/__init__.py
alpha_automl/wrapper_primitives/fasttext.py
alpha_automl/wrapper_primitives/huggingface_image.py
alpha_automl-0.3.0.dist-info/LICENSE.txt
alpha_automl-0.3.0.dist-info/METADATA
alpha_automl-0.3.0.dist-info/NOTICE.txt
alpha_automl-0.3.0.dist-info/WHEEL
alpha_automl-0.3.0.dist-info/top_level.txt
alpha_automl-0.3.0.dist-info/RECORD
