Metadata-Version: 2.1
Name: alpha-automl
Version: 0.3.0
Summary: Alpha-AutoML: NYU's AutoML System
Home-page: https://github.com/VIDA-NYU/alpha-automl
Author: Roque Lopez, Eden Wu, Aécio Santos, Remi Rampin
Author-email: rlopez@nyu.edu, eden.wu@nyu.edu, aecio.santos@nyu.edu, remi.rampin@nyu.edu
Maintainer: Roque Lopez, Eden Wu, Aécio Santos, Remi Rampin
Maintainer-email: rlopez@nyu.edu, eden.wu@nyu.edu, aecio.santos@nyu.edu, remi.rampin@nyu.edu
License: Apache-2.0
Keywords: datadrivendiscovery,automl,nyu
Platform: UNKNOWN
Classifier: Development Status :: 5 - Production/Stable
Classifier: Intended Audience :: Science/Research
Classifier: License :: OSI Approved :: Apache Software License
Classifier: Topic :: Scientific/Engineering
License-File: LICENSE.txt
License-File: NOTICE.txt
Requires-Dist: scipy
Requires-Dist: scikit-learn
Requires-Dist: torch (>=1.7)
Requires-Dist: nltk
Requires-Dist: pipelineprofiler
Requires-Dist: pandas
Requires-Dist: datamart-profiler
Requires-Dist: feature-engine
Requires-Dist: xgboost
Requires-Dist: lightgbm
Requires-Dist: numpy
Provides-Extra: fasttext-wheel
Requires-Dist: fasttext-wheel ; extra == 'fasttext-wheel'
Provides-Extra: full
Requires-Dist: imageio[pyav] ; extra == 'full'
Requires-Dist: pandas ; extra == 'full'
Requires-Dist: mxnet ; extra == 'full'
Requires-Dist: pmdarima ; extra == 'full'
Requires-Dist: gluonts ; extra == 'full'
Requires-Dist: fasttext-wheel ; extra == 'full'
Requires-Dist: scikit-image ; extra == 'full'
Requires-Dist: neuralforecast ; extra == 'full'
Requires-Dist: imageio[opencv] ; extra == 'full'
Requires-Dist: numpy (==1.23.5) ; extra == 'full'
Requires-Dist: transformers ; extra == 'full'
Provides-Extra: gluonts
Requires-Dist: gluonts ; extra == 'gluonts'
Provides-Extra: image
Requires-Dist: imageio[opencv] ; extra == 'image'
Requires-Dist: imageio[pyav] ; extra == 'image'
Requires-Dist: transformers ; extra == 'image'
Requires-Dist: scikit-image ; extra == 'image'
Provides-Extra: imageio_opencv_
Requires-Dist: imageio[opencv] ; extra == 'imageio_opencv_'
Provides-Extra: imageio_pyav_
Requires-Dist: imageio[pyav] ; extra == 'imageio_pyav_'
Provides-Extra: mxnet
Requires-Dist: mxnet ; extra == 'mxnet'
Provides-Extra: neuralforecast
Requires-Dist: neuralforecast ; extra == 'neuralforecast'
Provides-Extra: nlp
Requires-Dist: transformers ; extra == 'nlp'
Requires-Dist: fasttext-wheel ; extra == 'nlp'
Provides-Extra: numpy
Requires-Dist: numpy (==1.23.5) ; extra == 'numpy'
Provides-Extra: pandas
Requires-Dist: pandas ; extra == 'pandas'
Provides-Extra: pmdarima
Requires-Dist: pmdarima ; extra == 'pmdarima'
Provides-Extra: scikit-image
Requires-Dist: scikit-image ; extra == 'scikit-image'
Provides-Extra: timeseries
Requires-Dist: pandas ; extra == 'timeseries'
Requires-Dist: mxnet ; extra == 'timeseries'
Requires-Dist: pmdarima ; extra == 'timeseries'
Requires-Dist: gluonts ; extra == 'timeseries'
Requires-Dist: neuralforecast ; extra == 'timeseries'
Requires-Dist: numpy (==1.23.5) ; extra == 'timeseries'
Provides-Extra: transformers
Requires-Dist: transformers ; extra == 'transformers'
